[
  {
    "type": "argument",
    "named": true,
    "fields": {},
    "children": {
      "multiple": false,
      "required": true,
      "types": [
        {
          "type": "identifier",
          "named": true
        },
        {
          "type": "jump_label_reference",
          "named": true
        },
        {
          "type": "literal",
          "named": true
        },
        {
          "type": "parameter_usage",
          "named": true
        }
      ]
    }
  },
  {
    "type": "arguments",
    "named": true,
    "fields": {},
    "children": {
      "multiple": true,
      "required": true,
      "types": [
        {
          "type": "argument",
          "named": true
        }
      ]
    }
  },
  {
    "type": "block",
    "named": true,
    "fields": {},
    "children": {
      "multiple": true,
      "required": false,
      "types": [
        {
          "type": "comment",
          "named": true
        },
        {
          "type": "jump_label_definition",
          "named": true
        },
        {
          "type": "jump_label_reference",
          "named": true
        },
        {
          "type": "literal",
          "named": true
        },
        {
          "type": "macro_call",
          "named": true
        },
        {
          "type": "opcode",
          "named": true
        },
        {
          "type": "parameter_usage",
          "named": true
        }
      ]
    }
  },
  {
    "type": "jump_label_definition",
    "named": true,
    "fields": {
      "name": {
        "multiple": false,
        "required": true,
        "types": [
          {
            "type": "label_name",
            "named": true
          }
        ]
      }
    }
  },
  {
    "type": "jump_label_reference",
    "named": true,
    "fields": {},
    "children": {
      "multiple": false,
      "required": true,
      "types": [
        {
          "type": "label_name",
          "named": true
        }
      ]
    }
  },
  {
    "type": "literal",
    "named": true,
    "fields": {},
    "children": {
      "multiple": false,
      "required": true,
      "types": [
        {
          "type": "hex_literal",
          "named": true
        },
        {
          "type": "number",
          "named": true
        }
      ]
    }
  },
  {
    "type": "macro_call",
    "named": true,
    "fields": {},
    "children": {
      "multiple": true,
      "required": true,
      "types": [
        {
          "type": "arguments",
          "named": true
        },
        {
          "type": "macro_name",
          "named": true
        }
      ]
    }
  },
  {
    "type": "macro_definition",
    "named": true,
    "fields": {},
    "children": {
      "multiple": true,
      "required": true,
      "types": [
        {
          "type": "block",
          "named": true
        },
        {
          "type": "macro_name",
          "named": true
        },
        {
          "type": "parameter_list",
          "named": true
        },
        {
          "type": "returns_clause",
          "named": true
        },
        {
          "type": "takes_clause",
          "named": true
        }
      ]
    }
  },
  {
    "type": "opcode",
    "named": true,
    "fields": {}
  },
  {
    "type": "parameter",
    "named": true,
    "fields": {},
    "children": {
      "multiple": false,
      "required": true,
      "types": [
        {
          "type": "identifier",
          "named": true
        }
      ]
    }
  },
  {
    "type": "parameter_list",
    "named": true,
    "fields": {},
    "children": {
      "multiple": false,
      "required": false,
      "types": [
        {
          "type": "parameters",
          "named": true
        }
      ]
    }
  },
  {
    "type": "parameter_usage",
    "named": true,
    "fields": {
      "name": {
        "multiple": false,
        "required": true,
        "types": [
          {
            "type": "identifier",
            "named": true
          }
        ]
      }
    }
  },
  {
    "type": "parameters",
    "named": true,
    "fields": {},
    "children": {
      "multiple": true,
      "required": true,
      "types": [
        {
          "type": "parameter",
          "named": true
        }
      ]
    }
  },
  {
    "type": "preprocessor",
    "named": true,
    "fields": {},
    "children": {
      "multiple": false,
      "required": true,
      "types": [
        {
          "type": "string",
          "named": true
        }
      ]
    }
  },
  {
    "type": "returns_clause",
    "named": true,
    "fields": {},
    "children": {
      "multiple": false,
      "required": true,
      "types": [
        {
          "type": "number",
          "named": true
        }
      ]
    }
  },
  {
    "type": "solidity_function",
    "named": true,
    "fields": {
      "name": {
        "multiple": false,
        "required": true,
        "types": [
          {
            "type": "identifier",
            "named": true
          }
        ]
      }
    },
    "children": {
      "multiple": true,
      "required": false,
      "types": [
        {
          "type": "solidity_parameter_types",
          "named": true
        },
        {
          "type": "solidity_return_types",
          "named": true
        }
      ]
    }
  },
  {
    "type": "solidity_parameter_types",
    "named": true,
    "fields": {}
  },
  {
    "type": "solidity_return_types",
    "named": true,
    "fields": {}
  },
  {
    "type": "source_file",
    "named": true,
    "root": true,
    "fields": {},
    "children": {
      "multiple": true,
      "required": false,
      "types": [
        {
          "type": "comment",
          "named": true
        },
        {
          "type": "jump_label_definition",
          "named": true
        },
        {
          "type": "macro_definition",
          "named": true
        },
        {
          "type": "preprocessor",
          "named": true
        },
        {
          "type": "solidity_function",
          "named": true
        }
      ]
    }
  },
  {
    "type": "takes_clause",
    "named": true,
    "fields": {},
    "children": {
      "multiple": false,
      "required": true,
      "types": [
        {
          "type": "number",
          "named": true
        }
      ]
    }
  },
  {
    "type": "#define",
    "named": false
  },
  {
    "type": "#include",
    "named": false
  },
  {
    "type": "(",
    "named": false
  },
  {
    "type": ")",
    "named": false
  },
  {
    "type": ",",
    "named": false
  },
  {
    "type": ":",
    "named": false
  },
  {
    "type": "<",
    "named": false
  },
  {
    "type": "=",
    "named": false
  },
  {
    "type": ">",
    "named": false
  },
  {
    "type": "add",
    "named": false
  },
  {
    "type": "and",
    "named": false
  },
  {
    "type": "calldataload",
    "named": false
  },
  {
    "type": "comment",
    "named": true,
    "extra": true
  },
  {
    "type": "dup1",
    "named": false
  },
  {
    "type": "function",
    "named": false
  },
  {
    "type": "hex_literal",
    "named": true
  },
  {
    "type": "identifier",
    "named": true
  },
  {
    "type": "iszero",
    "named": false
  },
  {
    "type": "jump",
    "named": false
  },
  {
    "type": "jumpi",
    "named": false
  },
  {
    "type": "label_name",
    "named": true
  },
  {
    "type": "macro",
    "named": false
  },
  {
    "type": "macro_name",
    "named": true
  },
  {
    "type": "mstore",
    "named": false
  },
  {
    "type": "nonpayable",
    "named": false
  },
  {
    "type": "number",
    "named": true
  },
  {
    "type": "payable",
    "named": false
  },
  {
    "type": "pure",
    "named": false
  },
  {
    "type": "returns",
    "named": false
  },
  {
    "type": "revert",
    "named": false
  },
  {
    "type": "shr",
    "named": false
  },
  {
    "type": "string",
    "named": true
  },
  {
    "type": "swap1",
    "named": false
  },
  {
    "type": "takes",
    "named": false
  },
  {
    "type": "view",
    "named": false
  },
  {
    "type": "{",
    "named": false
  },
  {
    "type": "}",
    "named": false
  }
]